minty_pyramid/__init__.py
minty_pyramid/exception_handlers.py
minty_pyramid/generic_loader.py
minty_pyramid/loader.py
minty_pyramid/oidc.py
minty_pyramid/py.typed
minty_pyramid/renderer.py
minty_pyramid/session_manager.py
minty_pyramid/code_generation/__init__.py
minty_pyramid/code_generation/entities.py
minty_pyramid/code_generation/generate.py
minty_pyramid/code_generation/openapi.py
minty_pyramid/code_generation/templates/apidocs_test.j2
minty_pyramid/code_generation/templates/apidocs_view.j2
minty_pyramid/code_generation/templates/base_template.j2
minty_pyramid/code_generation/templates/routes.j2
minty_pyramid/code_generation/templates/test_routes.j2
minty_pyramid/code_generation/templates/views.j2
minty_pyramid/utils/__init__.py
minty_pyramid/utils/mockers.py
minty_pyramid/views/__init__.py
minty_pyramid/views/pydantic_entity.py
minty_pyramid-3.0.2.dist-info/METADATA
minty_pyramid-3.0.2.dist-info/WHEEL
minty_pyramid-3.0.2.dist-info/entry_points.txt
minty_pyramid-3.0.2.dist-info/top_level.txt
minty_pyramid-3.0.2.dist-info/RECORD
