Metadata-Version: 2.1
Name: minty-pyramid
Version: 3.0.2
Summary: Minty HTTP Api server based on Pyramid
Home-page: https://gitlab.com/minty-python/minty-pyramid
Author: Michiel Ootjers
Author-email: michiel@mintlab.nl
License: EUPL license
Keywords: minty_pyramid
Classifier: Development Status :: 2 - Pre-Alpha
Classifier: Intended Audience :: Developers
Classifier: License :: OSI Approved :: European Union Public Licence 1.2 (EUPL 1.2)
Classifier: Natural Language :: English
Classifier: Programming Language :: Python :: 3.9
Requires-Dist: pyramid ~=2.0
Requires-Dist: waitress >=2.1.1,~=2.1
Requires-Dist: minty >=3.0.6,~=3.0
Requires-Dist: python-json-logger ~=2.0
Requires-Dist: jsonpath-ng ~=1.5
Requires-Dist: click ~=8.0
Requires-Dist: jinja2 ~=3.0
Requires-Dist: redis ~=4.0
Requires-Dist: wrapt ~=1.12
Requires-Dist: python-jose[cryptography] ~=3.2
Requires-Dist: orjson ~=3.6
